MultiFeatures/__init__.py
MultiFeatures/IndianRailway/__init__.py
MultiFeatures/IndianRailway/confirmtkt.py
MultiFeatures/IndianRailway/dataConfig.py
MultiFeatures/IndianRailway/errors.py
MultiFeatures/IndianRailway/ixigo.py
MultiFeatures/IndianRailway/redrail.py
MultiFeatures/IndianRailway/whereismytrain.py
MultiFeatures-1.1.0.dist-info/LICENSE
MultiFeatures-1.1.0.dist-info/METADATA
MultiFeatures-1.1.0.dist-info/WHEEL
MultiFeatures-1.1.0.dist-info/top_level.txt
MultiFeatures-1.1.0.dist-info/RECORD
